{"id":"MSG","type":"DataType","name":"Message Type","description":"This field contains the message type, trigger event, and the message structure ID for the message.","dataType":null,"dataTypeName":null,"length":0,"usage":null,"rpt":null,"tableId":null,"tableName":null,"sample":"","fields":[{"id":"MSG.1","type":"DataTypeComponent","position":"MSG.1","length":0,"dataType":"ID","dataTypeName":"Coded values for HL7 tables","usage":"O","rpt":"1","tableId":"0076","tableName":"Message type","name":"Message Type","description":"The first component is the message type code defined by HL7 table 0076 - Message type"},{"id":"MSG.2","type":"DataTypeComponent","position":"MSG.2","length":0,"dataType":"ID","dataTypeName":"Coded values for HL7 tables","usage":"O","rpt":"1","tableId":"0003","tableName":"Event type","name":"Trigger Event","description":"The second component is the trigger event code defined by HL7 table 0003 - Event type"},{"id":"MSG.3","type":"DataTypeComponent","position":"MSG.3","length":0,"dataType":"ID","dataTypeName":"Coded values for HL7 tables","usage":"O","rpt":"1","tableId":"0354","tableName":"Message structure","name":"Message Structure","description":"The third component is the abstract message structure code defined by HL7 Table 0354 - Message structure.  This table has two columns.  The first column contains the value of this code, which describes a particular HL7 “abstract message structure definition” in terms of segments, as defined in sections 2.11 and 2.11.1.  The second column of table 0354 lists the various HL7 trigger events that use the particular abstract message definition.  For example, the message structure code ADT_A01 describes the single abstract message structure used by the trigger events A01, A04, A05, A08, A13, A14, A28 and A31"}]}