{"id":"PIP","type":"DataType","name":"Privileges","description":null,"dataType":null,"dataTypeName":null,"length":0,"usage":null,"rpt":null,"tableId":null,"tableName":null,"sample":"","fields":[{"id":"PIP.1","type":"DataTypeComponent","position":"PIP.1","length":0,"dataType":"CE","dataTypeName":"Coded Element","usage":"O","rpt":"1","tableId":null,"tableName":null,"name":"Privilege","description":null},{"id":"PIP.2","type":"DataTypeComponent","position":"PIP.2","length":0,"dataType":"CE","dataTypeName":"Coded Element","usage":"O","rpt":"1","tableId":null,"tableName":null,"name":"Privilege Class","description":null},{"id":"PIP.3","type":"DataTypeComponent","position":"PIP.3","length":0,"dataType":"DT","dataTypeName":"Date","usage":"O","rpt":"1","tableId":null,"tableName":null,"name":"Expiration Date","description":null},{"id":"PIP.4","type":"DataTypeComponent","position":"PIP.4","length":0,"dataType":"DT","dataTypeName":"Date","usage":"O","rpt":"1","tableId":null,"tableName":null,"name":"Activation Date","description":null},{"id":"PIP.5","type":"DataTypeComponent","position":"PIP.5","length":0,"dataType":"EI","dataTypeName":"Entity Identifier","usage":"O","rpt":"1","tableId":null,"tableName":null,"name":"Facility","description":null}]}