{"id":"NSC","segmentId":"NSC","longName":"Application Status Change","description":"The NSC segment is used to inform (NMR query response) or announce (NMD unsolicited update) the start up, shut down, and/or migration (to a different CPU or file server/file system) of a particular application. \r\n\r\nUsage Notes: \r\nFields 2-9.  These are not applicable (\"n/a\") when the type of change being requested or reported is start-up or shut-down.  If the change is of type \"M\", at least one of fields 2-5 must be different from its corresponding field in range 6-9.\r\nFields 4-5, 8-9.  See definitions for the MSH, message header segment, in Chapter 2, \"Control Section,\" for fields 3-4, for system and facility.  \"Application\" is available for interfacing with lower level protocols.  \"Facility\" is entirely site-defined.\r\nFields 2-3, 6-7: entirely site-defined.","sample":"","chapters":["CH_14"],"fields":[{"id":"NSC.1","type":"Field","position":"NSC.1","length":0,"dataType":"CWE","dataTypeName":"Coded With Exceptions","usage":"R","rpt":"1","tableId":"0409","tableName":"Application Change Type","name":"Application Change Type","description":null},{"id":"NSC.2","type":"Field","position":"NSC.2","length":0,"dataType":"ST","dataTypeName":"String Data","usage":"O","rpt":"1","tableId":null,"tableName":null,"name":"Current Cpu","description":null},{"id":"NSC.3","type":"Field","position":"NSC.3","length":0,"dataType":"ST","dataTypeName":"String Data","usage":"O","rpt":"1","tableId":null,"tableName":null,"name":"Current Fileserver","description":null},{"id":"NSC.4","type":"Field","position":"NSC.4","length":0,"dataType":"HD","dataTypeName":"Hierarchic Designator","usage":"O","rpt":"1","tableId":"0361","tableName":"Application","name":"Current Application","description":null},{"id":"NSC.5","type":"Field","position":"NSC.5","length":0,"dataType":"HD","dataTypeName":"Hierarchic Designator","usage":"O","rpt":"1","tableId":"0362","tableName":"Facility","name":"Current Facility","description":null},{"id":"NSC.6","type":"Field","position":"NSC.6","length":0,"dataType":"ST","dataTypeName":"String Data","usage":"O","rpt":"1","tableId":null,"tableName":null,"name":"New Cpu","description":null},{"id":"NSC.7","type":"Field","position":"NSC.7","length":0,"dataType":"ST","dataTypeName":"String Data","usage":"O","rpt":"1","tableId":null,"tableName":null,"name":"New Fileserver","description":null},{"id":"NSC.8","type":"Field","position":"NSC.8","length":0,"dataType":"HD","dataTypeName":"Hierarchic Designator","usage":"O","rpt":"1","tableId":"0361","tableName":"Application","name":"New Application","description":null},{"id":"NSC.9","type":"Field","position":"NSC.9","length":0,"dataType":"HD","dataTypeName":"Hierarchic Designator","usage":"O","rpt":"1","tableId":"0362","tableName":"Facility","name":"New Facility","description":null}]}