{"id":"EDR_R07","msgStructId":"EDR_R07","eventDesc":"Enhanced Display Response","description":"This section is retained for backward compatibility as of V2.4.","sample":null,"chapters":["CH_05"],"segments":[{"id":"MSH","name":"MSH","longName":"Message Header","sequence":"1","usage":"R","rpt":"1","isGroup":false,"segments":null},{"id":"SFT","name":"SFT","longName":"Software Segment","sequence":"2","usage":"O","rpt":"*","isGroup":false,"segments":null},{"id":"MSA","name":"MSA","longName":"Message Acknowledgment","sequence":"3","usage":"R","rpt":"1","isGroup":false,"segments":null},{"id":"ERR","name":"ERR","longName":"Error","sequence":"4","usage":"O","rpt":"1","isGroup":false,"segments":null},{"id":"QAK","name":"QAK","longName":"Query Acknowledgment","sequence":"5","usage":"R","rpt":"1","isGroup":false,"segments":null},{"id":"DSP","name":"DSP","longName":"Display Data","sequence":"6","usage":"R","rpt":"*","isGroup":false,"segments":null},{"id":"DSC","name":"DSC","longName":"Continuation Pointer","sequence":"7","usage":"O","rpt":"1","isGroup":false,"segments":null}]}