{"id":"SCN_S37","msgStructId":"SCN_S37","eventDesc":"Notification of Anti-Microbial Device Cycle Data","description":"This message is sent from a filler application to notify other applications that anti-microbial device cycle data has been generated.  The information in the SCN segment and the other detail segments as appropriate describe details of a sterilization or decontamination cycle.","sample":null,"chapters":["CH_17"],"segments":[{"id":"MSH","name":"MSH","longName":"Message Header","sequence":"1","usage":"R","rpt":"1","isGroup":false,"segments":null},{"id":"SFT","name":"SFT","longName":"Software Segment","sequence":"2","usage":"O","rpt":"*","isGroup":false,"segments":null},{"id":"UAC","name":"UAC","longName":"User Authentication Credential","sequence":"3","usage":"O","rpt":"1","isGroup":false,"segments":null},{"id":null,"name":"ANTI MICROBIAL DEVICE CYCLE DATA","longName":null,"sequence":null,"usage":"R","rpt":"*","isGroup":true,"segments":[{"id":"SDD","name":"SDD","longName":"Sterilization Device Data","sequence":"4","usage":"R","rpt":"1","isGroup":false,"segments":null},{"id":"SCD","name":"SCD","longName":"Anti-Microbial Cycle Data","sequence":"5","usage":"O","rpt":"*","isGroup":false,"segments":null}]}]}