{"id":"0278","tableId":"0278","tableType":"User","name":"Filler status codes","chapters":["CH_10"],"entries":[{"value":"BLOCKED","description":"The indicated time slot(s) is(are) blocked. Not used in the AIS,  AIG,  AIL,  AIP segments.","comment":null},{"value":"BOOKED","description":"The indicated appointment is booked","comment":null},{"value":"CANCELLED","description":"The indicated appointment was stopped from occurring (cancelled prior to starting)","comment":null},{"value":"COMPLETE","description":"The indicated appointment has completed normally (was not discontinued, canceled, or deleted)","comment":null},{"value":"DC","description":"The indicated appointment was discontinued (DCed while in progress, discontinued parent appointment,  or discontinued child appointment)","comment":null},{"value":"DELETED","description":"The indicated appointment was deleted from the filler application","comment":null},{"value":"OVERBOOK","description":"The appointment has been confirmed; however it is confirmed in an overbooked state","comment":null},{"value":"PENDING","description":"Appointment has not yet been confirmed","comment":null},{"value":"STARTED","description":"The indicated appointment has begun and is currently in progress","comment":null},{"value":"WAITLIST","description":"Appointment has been placed on a waiting list for a particular slot, or set of slots","comment":null}]}