{"id":"OBX","segmentId":"OBX","longName":"Observation/Result","description":"The OBX segment is used to transmit a single observation or observation fragment. It represents the smallest indivisible unit of a report. The OBX segment can also contain encapsulated data, e.g., a CDA document or a DICOM image.\r\n\r\nIts principal mission is to carry information about observations in report messages.  But the OBX can also be part of an observation order.  In this case, the OBX carries clinical information needed by the filler to interpret the observation the filler makes.  For example, an OBX is needed to report the inspired oxygen on an order for a blood oxygen to a blood gas lab, or to report the menstrual phase information which should be included on an order for a pap smear to a cytology lab.  Appendix 7A includes codes for identifying many of pieces of information needed by observation producing services to properly interpret a test result.  OBX is also found in other HL7 messages that need to include patient clinical information. ","sample":"","chapters":["CH_07","CH_09"],"fields":[{"id":"OBX.1","type":"Field","position":"OBX.1","length":4,"dataType":"SI","dataTypeName":"Sequence ID","usage":"O","rpt":"1","tableId":null,"tableName":null,"name":"Set ID - OBX","description":null},{"id":"OBX.2","type":"Field","position":"OBX.2","length":2,"dataType":"ID","dataTypeName":"Coded values for HL7 tables","usage":"C","rpt":"1","tableId":"0125","tableName":"Value type","name":"Value Type","description":null},{"id":"OBX.3","type":"Field","position":"OBX.3","length":250,"dataType":"CE","dataTypeName":"Coded Element","usage":"R","rpt":"1","tableId":null,"tableName":null,"name":"Observation Identifier","description":null},{"id":"OBX.4","type":"Field","position":"OBX.4","length":20,"dataType":"ST","dataTypeName":"String Data","usage":"C","rpt":"1","tableId":null,"tableName":null,"name":"Observation Sub-ID","description":null},{"id":"OBX.5","type":"Field","position":"OBX.5","length":99999,"dataType":"VARIES","dataTypeName":"Variable Datatype","usage":"C","rpt":"*","tableId":null,"tableName":null,"name":"Observation Value","description":null},{"id":"OBX.6","type":"Field","position":"OBX.6","length":250,"dataType":"CE","dataTypeName":"Coded Element","usage":"O","rpt":"1","tableId":null,"tableName":null,"name":"Units","description":null},{"id":"OBX.7","type":"Field","position":"OBX.7","length":60,"dataType":"ST","dataTypeName":"String Data","usage":"O","rpt":"1","tableId":null,"tableName":null,"name":"References Range","description":null},{"id":"OBX.8","type":"Field","position":"OBX.8","length":5,"dataType":"IS","dataTypeName":"Coded value for user-defined tables","usage":"O","rpt":"*","tableId":"0078","tableName":"Abnormal flags","name":"Abnormal Flags","description":null},{"id":"OBX.9","type":"Field","position":"OBX.9","length":5,"dataType":"NM","dataTypeName":"Numeric","usage":"O","rpt":"1","tableId":null,"tableName":null,"name":"Probability","description":null},{"id":"OBX.10","type":"Field","position":"OBX.10","length":2,"dataType":"ID","dataTypeName":"Coded values for HL7 tables","usage":"O","rpt":"*","tableId":"0080","tableName":"Nature of Abnormal Testing","name":"Nature of Abnormal Test","description":null},{"id":"OBX.11","type":"Field","position":"OBX.11","length":1,"dataType":"ID","dataTypeName":"Coded values for HL7 tables","usage":"R","rpt":"1","tableId":"0085","tableName":"Observation result status codes interpretation","name":"Observation Result Status","description":null},{"id":"OBX.12","type":"Field","position":"OBX.12","length":26,"dataType":"TS","dataTypeName":"Time Stamp","usage":"O","rpt":"1","tableId":null,"tableName":null,"name":"Effective Date of Reference Range","description":null},{"id":"OBX.13","type":"Field","position":"OBX.13","length":20,"dataType":"ST","dataTypeName":"String Data","usage":"O","rpt":"1","tableId":null,"tableName":null,"name":"User Defined Access Checks","description":null},{"id":"OBX.14","type":"Field","position":"OBX.14","length":26,"dataType":"TS","dataTypeName":"Time Stamp","usage":"O","rpt":"1","tableId":null,"tableName":null,"name":"Date/Time of the Observation","description":null},{"id":"OBX.15","type":"Field","position":"OBX.15","length":250,"dataType":"CE","dataTypeName":"Coded Element","usage":"O","rpt":"1","tableId":null,"tableName":null,"name":"Producer's ID","description":null},{"id":"OBX.16","type":"Field","position":"OBX.16","length":250,"dataType":"XCN","dataTypeName":"Extended Composite ID Number and Name for Persons","usage":"O","rpt":"*","tableId":null,"tableName":null,"name":"Responsible Observer","description":null},{"id":"OBX.17","type":"Field","position":"OBX.17","length":250,"dataType":"CE","dataTypeName":"Coded Element","usage":"O","rpt":"*","tableId":null,"tableName":null,"name":"Observation Method","description":null},{"id":"OBX.18","type":"Field","position":"OBX.18","length":22,"dataType":"EI","dataTypeName":"Entity Identifier","usage":"O","rpt":"*","tableId":null,"tableName":null,"name":"Equipment Instance Identifier","description":null},{"id":"OBX.19","type":"Field","position":"OBX.19","length":26,"dataType":"TS","dataTypeName":"Time Stamp","usage":"O","rpt":"1","tableId":null,"tableName":null,"name":"Date/Time of the Analysis","description":null},{"id":"OBX.20","type":"Field","position":"OBX.20","length":0,"dataType":"ST","dataTypeName":"String Data","usage":"X","rpt":"1","tableId":null,"tableName":null,"name":"Reserved for harmonization with V2.6 ","description":null},{"id":"OBX.21","type":"Field","position":"OBX.21","length":0,"dataType":"ST","dataTypeName":"String Data","usage":"X","rpt":"1","tableId":null,"tableName":null,"name":"Reserved for harmonization with V2.6","description":null},{"id":"OBX.22","type":"Field","position":"OBX.22","length":0,"dataType":"ST","dataTypeName":"String Data","usage":"X","rpt":"1","tableId":null,"tableName":null,"name":"Reserved for harmonization with V2.6","description":null},{"id":"OBX.23","type":"Field","position":"OBX.23","length":567,"dataType":"XON","dataTypeName":"Extended Composite Name and Identification Number for Organizations","usage":"O","rpt":"1","tableId":null,"tableName":null,"name":"Performing Organization Name","description":null},{"id":"OBX.24","type":"Field","position":"OBX.24","length":631,"dataType":"XAD","dataTypeName":"Extended Address","usage":"O","rpt":"1","tableId":null,"tableName":null,"name":"Performing Organization Address","description":null},{"id":"OBX.25","type":"Field","position":"OBX.25","length":3002,"dataType":"XCN","dataTypeName":"Extended Composite ID Number and Name for Persons","usage":"O","rpt":"1","tableId":null,"tableName":null,"name":"Performing Organization Medical Director","description":null}]}