{"id":"0122","tableId":"0122","tableType":"HL7","name":"Charge Type","chapters":["CH_02"],"entries":[{"value":"CH","description":"Charge","comment":null},{"value":"CO","description":"Contract","comment":null},{"value":"CR","description":"Credit","comment":null},{"value":"DP","description":"Department","comment":null},{"value":"GR","description":"Grant","comment":null},{"value":"NC","description":"No Charge","comment":null},{"value":"PC","description":"Professional","comment":null},{"value":"RS","description":"Research","comment":null}]}