{"id":"QRD","segmentId":"QRD","longName":"Original-Style Query Definition","description":"The QRD segment is used to define a query.","sample":"","chapters":["CH_05"],"fields":[{"id":"QRD.1","type":"Field","position":"QRD.1","length":26,"dataType":"TS","dataTypeName":"Time Stamp","usage":"R","rpt":"1","tableId":null,"tableName":null,"name":"Query Date/Time","description":null},{"id":"QRD.2","type":"Field","position":"QRD.2","length":1,"dataType":"ID","dataTypeName":"Coded values for HL7 tables","usage":"R","rpt":"1","tableId":"0106","tableName":"Query/response format code","name":"Query Format Code","description":null},{"id":"QRD.3","type":"Field","position":"QRD.3","length":1,"dataType":"ID","dataTypeName":"Coded values for HL7 tables","usage":"R","rpt":"1","tableId":"0091","tableName":"Query priority","name":"Query Priority","description":null},{"id":"QRD.4","type":"Field","position":"QRD.4","length":10,"dataType":"ST","dataTypeName":"String Data","usage":"R","rpt":"1","tableId":null,"tableName":null,"name":"Query ID","description":null},{"id":"QRD.5","type":"Field","position":"QRD.5","length":1,"dataType":"ID","dataTypeName":"Coded values for HL7 tables","usage":"O","rpt":"1","tableId":"0107","tableName":"Deferred response type","name":"Deferred Response Type","description":null},{"id":"QRD.6","type":"Field","position":"QRD.6","length":26,"dataType":"TS","dataTypeName":"Time Stamp","usage":"O","rpt":"1","tableId":null,"tableName":null,"name":"Deferred Response Date/Time","description":null},{"id":"QRD.7","type":"Field","position":"QRD.7","length":10,"dataType":"CQ","dataTypeName":"Composite Quantity With Units","usage":"R","rpt":"1","tableId":null,"tableName":null,"name":"Quantity Limited Request","description":null},{"id":"QRD.8","type":"Field","position":"QRD.8","length":250,"dataType":"XCN","dataTypeName":"Extended Composite ID Number And Name For Persons","usage":"R","rpt":"*","tableId":null,"tableName":null,"name":"Who Subject Filter","description":null},{"id":"QRD.9","type":"Field","position":"QRD.9","length":250,"dataType":"CE","dataTypeName":"Coded Element","usage":"R","rpt":"*","tableId":"0048","tableName":"What subject filter","name":"What Subject Filter","description":null},{"id":"QRD.10","type":"Field","position":"QRD.10","length":250,"dataType":"CE","dataTypeName":"Coded Element","usage":"R","rpt":"*","tableId":null,"tableName":null,"name":"What Department Data Code","description":null},{"id":"QRD.11","type":"Field","position":"QRD.11","length":20,"dataType":"VR","dataTypeName":"Value Qualifier","usage":"O","rpt":"*","tableId":null,"tableName":null,"name":"What Data Code Value Qual.","description":null},{"id":"QRD.12","type":"Field","position":"QRD.12","length":1,"dataType":"ID","dataTypeName":"Coded values for HL7 tables","usage":"O","rpt":"1","tableId":"0108","tableName":"Query results level","name":"Query Results Level","description":null}]}