{"id":"MFN_M05","msgStructId":"MFN_M05","eventDesc":"Patient location master file","description":null,"sample":null,"chapters":["CH_08"],"segments":[{"id":"MSH","name":"MSH","longName":"Message header segment","sequence":"1","usage":"R","rpt":"1","isGroup":false,"segments":null},{"id":"MFI","name":"MFI","longName":"Master file identification segment","sequence":"2","usage":"R","rpt":"1","isGroup":false,"segments":null},{"id":null,"name":"MF LOCATION","longName":null,"sequence":null,"usage":"R","rpt":"*","isGroup":true,"segments":[{"id":"MFE","name":"MFE","longName":"Master file entry segment","sequence":"3","usage":"R","rpt":"1","isGroup":false,"segments":null},{"id":"LOC","name":"LOC","longName":"Location identification segment","sequence":"4","usage":"R","rpt":"1","isGroup":false,"segments":null},{"id":"LCH","name":"LCH","longName":"Location characteristic segment","sequence":"5","usage":"O","rpt":"*","isGroup":false,"segments":null},{"id":"LRL","name":"LRL","longName":"Location relationship segment","sequence":"6","usage":"O","rpt":"*","isGroup":false,"segments":null},{"id":null,"name":"MF LOC DEPT","longName":null,"sequence":null,"usage":"R","rpt":"*","isGroup":true,"segments":[{"id":"LDP","name":"LDP","longName":"Location department segment","sequence":"7","usage":"R","rpt":"1","isGroup":false,"segments":null},{"id":"LCH","name":"LCH","longName":"Location characteristic segment","sequence":"8","usage":"O","rpt":"*","isGroup":false,"segments":null},{"id":"LCC","name":"LCC","longName":"Location charge code segment","sequence":"9","usage":"O","rpt":"*","isGroup":false,"segments":null}]}]}]}