{"id":"CCQ_I19","msgStructId":"CCQ_I19","eventDesc":"Collaborative Care Query/Collaborative Care Query Update","description":"This event triggers a query message to be sent from a referring healthcare provider to a referred to healthcare provider, regarding a specific, previously sent collaborative care referral. The Collaborative Care Query message must contain sufficient data for the referred to provider to be able to identify the specific referral being queried. The response to a Collaborative Care Query message is a CQU - Collaborative Care Query Update message. The meaning of the Collaborative Care Query Update message is identical to the meaning of the Asynchronous Collaborative Care Update message.","sample":null,"chapters":["CH_11"],"segments":[{"id":"MSH","name":"MSH","longName":"Message Header","sequence":"1","usage":"R","rpt":"1","isGroup":false,"segments":null},{"id":"SFT","name":"SFT","longName":"Software Segment","sequence":"2","usage":"O","rpt":"*","isGroup":false,"segments":null},{"id":"UAC","name":"UAC","longName":"User Authentication Credential Segment","sequence":"3","usage":"O","rpt":"1","isGroup":false,"segments":null},{"id":"RF1","name":"RF1","longName":"Referral Information","sequence":"4","usage":"R","rpt":"1","isGroup":false,"segments":null},{"id":null,"name":"PROVIDER_CONTACT","longName":null,"sequence":null,"usage":"O","rpt":"*","isGroup":true,"segments":[{"id":"PRD","name":"PRD","longName":"Provider Data","sequence":"5","usage":"R","rpt":"1","isGroup":false,"segments":null},{"id":"CTD","name":"CTD","longName":"Contact Data","sequence":"6","usage":"O","rpt":"*","isGroup":false,"segments":null}]},{"id":"REL","name":"REL","longName":"Clinical Relationship Segment","sequence":"7","usage":"O","rpt":"*","isGroup":false,"segments":null}]}