{"id":"CN_PHYSICIAN","type":"DataType","name":"Cn For Physicians","description":null,"dataType":null,"dataTypeName":null,"length":0,"usage":null,"rpt":null,"tableId":null,"tableName":null,"sample":"","fields":[{"id":"CN_PHYSICIAN.1","type":"DataTypeComponent","position":"CN_PHYSICIAN.1","length":0,"dataType":"ID","dataTypeName":"Coded Value","usage":"O","rpt":"1","tableId":null,"tableName":null,"name":"Physician Id","description":null},{"id":"CN_PHYSICIAN.2","type":"DataTypeComponent","position":"CN_PHYSICIAN.2","length":0,"dataType":"ST","dataTypeName":"String Data","usage":"O","rpt":"1","tableId":null,"tableName":null,"name":"Familiy Name","description":null},{"id":"CN_PHYSICIAN.3","type":"DataTypeComponent","position":"CN_PHYSICIAN.3","length":0,"dataType":"ST","dataTypeName":"String Data","usage":"O","rpt":"1","tableId":null,"tableName":null,"name":"Given Name","description":null},{"id":"CN_PHYSICIAN.4","type":"DataTypeComponent","position":"CN_PHYSICIAN.4","length":0,"dataType":"ST","dataTypeName":"String Data","usage":"O","rpt":"1","tableId":null,"tableName":null,"name":"Middle Initial Or Name","description":null},{"id":"CN_PHYSICIAN.5","type":"DataTypeComponent","position":"CN_PHYSICIAN.5","length":0,"dataType":"ST","dataTypeName":"String Data","usage":"O","rpt":"1","tableId":null,"tableName":null,"name":"Suffix (e.g. Jr Or Iii)","description":null},{"id":"CN_PHYSICIAN.6","type":"DataTypeComponent","position":"CN_PHYSICIAN.6","length":0,"dataType":"ST","dataTypeName":"String Data","usage":"O","rpt":"1","tableId":null,"tableName":null,"name":"Prefix (e.g. Dr)","description":null},{"id":"CN_PHYSICIAN.7","type":"DataTypeComponent","position":"CN_PHYSICIAN.7","length":0,"dataType":"ST","dataTypeName":"String Data","usage":"O","rpt":"1","tableId":null,"tableName":null,"name":"Degree (e.g. Md)","description":null},{"id":"CN_PHYSICIAN.8","type":"DataTypeComponent","position":"CN_PHYSICIAN.8","length":0,"dataType":"ID","dataTypeName":"Coded Value","usage":"O","rpt":"1","tableId":null,"tableName":null,"name":"Source Table Id","description":null}]}