{"id":"CDO","segmentId":"CDO","longName":"Cumulative Dosage","description":"The Cumulative Dosage segment allows for the communication of cumulative dosage limits that administrations against this medication order should stay within.  As part of one of the pharmacy messages, one may want to indicate one or more limits that apply, e.g., limit for the duration of the order, lifetime limit, or weekly limit","sample":"","chapters":["CH_04"],"fields":[{"id":"CDO.1","type":"Field","position":"CDO.1","length":0,"dataType":"SI","dataTypeName":"Sequence Id","usage":"O","rpt":"1","tableId":null,"tableName":null,"name":"Set ID – CDO","description":null},{"id":"CDO.2","type":"Field","position":"CDO.2","length":0,"dataType":"ID","dataTypeName":"Coded Value For Hl7 Defined Tables","usage":"O","rpt":"1","tableId":"0206","tableName":"Segment action code","name":"Action Code","description":null},{"id":"CDO.3","type":"Field","position":"CDO.3","length":0,"dataType":"CQ","dataTypeName":"Composite Quantity With Units","usage":"O","rpt":"1","tableId":null,"tableName":null,"name":"Cumulative Dosage Limit","description":null},{"id":"CDO.4","type":"Field","position":"CDO.4","length":0,"dataType":"CQ","dataTypeName":"Composite Quantity With Units","usage":"O","rpt":"1","tableId":"0924","tableName":"Cumulative Dosage Limit UoM","name":"Cumulative Dosage Limit Time Interval","description":null}]}