{"id":"NTE","segmentId":"NTE","longName":"Notes And Comments","description":"The NTE segment is defined here for inclusion in messages defined in other chapters. It is commonly used for sending notes and comments.\r\n\r\nThe technical committees define the meaning of the NTE segments within the context of the messages in their chapters. For each NTE, the description in the message attribute table should include an indication of the segment associated with the NTE, for example \"Notes and Comments for the PID\".","sample":"","chapters":["CH_02"],"fields":[{"id":"NTE.1","type":"Field","position":"NTE.1","length":0,"dataType":"SI","dataTypeName":"Sequence Id","usage":"O","rpt":"1","tableId":null,"tableName":null,"name":"Set Id - Nte","description":null},{"id":"NTE.2","type":"Field","position":"NTE.2","length":1,"dataType":"ID","dataTypeName":"Coded Value For Hl7 Defined Tables","usage":"O","rpt":"1","tableId":"0105","tableName":"Source of Comment","name":"Source Of Comment","description":null},{"id":"NTE.3","type":"Field","position":"NTE.3","length":0,"dataType":"FT","dataTypeName":"Formatted Text Data","usage":"O","rpt":"*","tableId":null,"tableName":null,"name":"Comment","description":null},{"id":"NTE.4","type":"Field","position":"NTE.4","length":0,"dataType":"CWE","dataTypeName":"Coded With Exceptions","usage":"O","rpt":"1","tableId":"0364","tableName":"Comment Type","name":"Comment Type","description":null},{"id":"NTE.5","type":"Field","position":"NTE.5","length":0,"dataType":"XCN","dataTypeName":"Extended Composite Id Number And Name For Persons","usage":"O","rpt":"1","tableId":null,"tableName":null,"name":"Entered By","description":null},{"id":"NTE.6","type":"Field","position":"NTE.6","length":0,"dataType":"DTM","dataTypeName":"Date/time","usage":"O","rpt":"1","tableId":null,"tableName":null,"name":"Entered Date/Time","description":null},{"id":"NTE.7","type":"Field","position":"NTE.7","length":0,"dataType":"DTM","dataTypeName":"Date/time","usage":"O","rpt":"1","tableId":null,"tableName":null,"name":"Effective Start Date","description":null},{"id":"NTE.8","type":"Field","position":"NTE.8","length":0,"dataType":"DTM","dataTypeName":"Date/time","usage":"O","rpt":"1","tableId":null,"tableName":null,"name":"Expiration Date","description":null}]}